diffpy/__init__.py
diffpy/distanceprinter/__init__.py
diffpy/distanceprinter/distanceprinter.py
diffpy/distanceprinter/distanceprinter_app.py
diffpy/distanceprinter/version.py
diffpy_distanceprinter-1.0.0.dist-info/licenses/AUTHORS.rst
diffpy_distanceprinter-1.0.0.dist-info/licenses/LICENSE.rst
diffpy_distanceprinter-1.0.0.dist-info/METADATA
diffpy_distanceprinter-1.0.0.dist-info/WHEEL
diffpy_distanceprinter-1.0.0.dist-info/entry_points.txt
diffpy_distanceprinter-1.0.0.dist-info/top_level.txt
diffpy_distanceprinter-1.0.0.dist-info/RECORD
