Metadata-Version: 2.4
Name: diffpy.distanceprinter
Version: 1.0.0
Summary: Distance Printer, calculate the inter atomic distances. Part of xPDFsuite
Author-email: "Simon J.L. Billinge Group" <sb2896@columbia.edu>
Maintainer-email: "Simon J.L. Billinge Group" <sb2896@columbia.edu>
Project-URL: Homepage, https://github.com/diffpy/diffpy.distanceprinter/
Project-URL: Issues, https://github.com/diffpy/diffpy.distanceprinter/issues/
Keywords: diffpy,pdf,data-interpretation
Classifier: Development Status :: 5 - Production/Stable
Classifier: Environment :: Console
Classifier: Intended Audience :: Developers
Classifier: Intended Audience :: Science/Research
Classifier: License :: OSI Approved :: BSD License
Classifier: Operating System :: MacOS :: MacOS X
Classifier: Operating System :: Microsoft :: Windows
Classifier: Operating System :: POSIX
Classifier: Operating System :: Unix
Classifier: Programming Language :: Python :: 3.11
Classifier: Programming Language :: Python :: 3.12
Classifier: Programming Language :: Python :: 3.13
Classifier: Topic :: Scientific/Engineering :: Physics
Classifier: Topic :: Scientific/Engineering :: Chemistry
Requires-Python: <3.14,>=3.11
License-File: LICENSE.rst
License-File: AUTHORS.rst
Requires-Dist: numpy
Requires-Dist: diffpy.pdffit2
Requires-Dist: diffpy.structure
Dynamic: license-file
